CHANGES.md
MANIFEST.in
README.md
setup.py
pbus/__init__.py
pbus/__init__.pyc
pbus/__main__.py
pbus/bus.py
pbus/bus.pyc
pbus.egg-info/PKG-INFO
pbus.egg-info/SOURCES.txt
pbus.egg-info/dependency_links.txt
pbus.egg-info/not-zip-safe
pbus.egg-info/top_level.txt
pbus/__pycache__/__init__.cpython-37.pyc
pbus/__pycache__/__main__.cpython-37.pyc
pbus/__pycache__/bus.cpython-37.pyc