Metadata-Version: 2.1
Name: pbus
Version: 1.5.0
Summary: A simple application layer event-bus lib, support redis/mqtt/rabbitmq/kafka.
Home-page: https://github.com/sintrb/pbus/
Author: trb
Author-email: sintrb@gmail.com
License: UNKNOWN
Keywords: pbus,bus,event,redis,rabbitmq,kafka
Platform: UNKNOWN
